aigenerate/__init__.py
aigenerate/chatgpt.py
aigenerate/settings.py
aigenerate-0.1.3.dist-info/METADATA
aigenerate-0.1.3.dist-info/WHEEL
aigenerate-0.1.3.dist-info/entry_points.txt
aigenerate-0.1.3.dist-info/RECORD
