Metadata-Version: 2.1
Name: aigenerate
Version: 0.1.3
Summary: 
Author: razens
Author-email: razens@gmail.com
Requires-Python: >=3.10,<4.0
Classifier: Programming Language :: Python :: 3
Classifier: Programming Language :: Python :: 3.10
Classifier: Programming Language :: Python :: 3.11
Requires-Dist: mypy (>=1.1.1,<2.0.0)
Requires-Dist: requests (>=2.28.2,<3.0.0)
Requires-Dist: stubs (>=1.0.0,<2.0.0)
Requires-Dist: types-requests (>=2.28.11.16,<3.0.0.0)
